vending_fsm.v
module vending_fsm (
    input  wire clk,
    input  wire rst,
    input  wire coin_5,
    input  wire coin_10,
    input  wire cancel,
    input  wire [1:0] select,
    output reg  dispense,
    output reg  refund,
    output reg  [1:0] product_id
);

    // giving vals to all main states
    parameter IDLE       = 2'b00,
              WAIT_COINS = 2'b01,
              DISPENSE   = 2'b10,
              REFUND     = 2'b11;

    reg [1:0] state, next_state; //declaring vars
    reg [7:0] balance;
    reg [7:0] price;

    // sequential -> takes action based on state and updates data
    always @(posedge clk or posedge rst) begin
        if (rst) begin //resets everything to defaults and zeroes
            state <= IDLE;
            balance <= 8'd0;
            product_id <= 2'b00;
        end else begin
            state <= next_state; //update the state on every clock edge

            // updating values for balance based on condition
            if (state == WAIT_COINS) begin
                if (coin_5)
                    balance <= balance + 8'd5;
                if (coin_10)
                    balance <= balance + 8'd10;
            end else begin
                balance <= 8'd0;
            end

            // if were idle and the user selects a product, store that product code
            if (state == IDLE && select != 2'b00)
                product_id <= select;
        end
    end

    // m the prices for each product here (note we are not working with product b00)
    always @(*) begin
        case (product_id)
            2'b00: price = 8'd10;
            2'b01: price = 8'd15;
            2'b10: price = 8'd20;
            2'b11: price = 8'd25;
            default: price = 8'd10;
        endcase
    end

    // combinational -> what is the next state i should go to?
    always @(*) begin
        next_state = state;
        dispense = 1'b0;
        refund = 1'b0;

        case (state)
            IDLE: begin
                if (select != 2'b00)
                    next_state = WAIT_COINS;
            end

            WAIT_COINS: begin
                if (cancel)
                    next_state = REFUND;
                else if (balance >= price)
                    next_state = DISPENSE;
            end

            DISPENSE: begin
                dispense = 1'b1;
                next_state = IDLE;
            end

            REFUND: begin
                refund = 1'b1;
                next_state = IDLE;
            end

            default: next_state = IDLE;
        endcase
    end

endmodule

tb_vending_fsm.v
// tb_vending_fsm.v
`timescale 1ns/1ps
module tb_vending_fsm;
    reg clk, rst;
    reg coin_5, coin_10, cancel;
    reg [1:0] select;
    wire dispense, refund;
    wire [1:0] product_id;

    // Instantiate DUT
    vending_fsm uut (
        .clk(clk),
        .rst(rst),
        .coin_5(coin_5),
        .coin_10(coin_10),
        .cancel(cancel),
        .select(select),
        .dispense(dispense),
        .refund(refund),
        .product_id(product_id)
    );

    // Clock generation
    initial begin
        clk = 0;
        forever #5 clk = ~clk;
    end

    // Test stimulus
    initial begin
        $dumpfile("vending.vcd");
        $dumpvars(0, tb_vending_fsm);

        // Initialization
        rst = 1;
        coin_5 = 0; coin_10 = 0; cancel = 0; select = 2'b00;
        #15 rst = 0;

        // Scenario 1: Product 01 (₹15)
        $display("\n--- Scenario 1: Product 01 ---");
        select = 2'b01; #10; select = 2'b00; //'pressing' the product 01 button 
        #10 coin_10 = 1; #10 coin_10 = 0;
        #10 coin_5 = 1; #10 coin_5 = 0;
        #30;

        // Scenario 2: Product 10 (₹20) then cancel
        $display("\n--- Scenario 2: Product 10 + Cancel ---");
        select = 2'b10; #10; select = 2'b00;
        #10 coin_10 = 1; #10 coin_10 = 0;
        #10 cancel = 1; #10 cancel = 0; //showing cancel functionality
        #40;

        // Scenario 3: Product 11 (₹25)
        $display("\n--- Scenario 3: Product 11 ---");
        select = 2'b11; #10; select = 2'b00;
        #10 coin_10 = 1; #10 coin_10 = 0;
        #10 coin_10 = 1; #10 coin_10 = 0;
        #10 coin_10 = 1; #10 coin_10 = 0;
        #50;


        $finish;
    end
endmodule

vending.vcd
$date
	Tue Nov 11 13:25:33 2025
$end
$version
	Icarus Verilog
$end
$timescale
	1ps
$end
$scope module tb_vending_fsm $end
$var wire 1 ! dispense $end
$var wire 2 " product_id [1:0] $end
$var wire 1 # refund $end
$var reg 1 $ cancel $end
$var reg 1 % clk $end
$var reg 1 & coin_10 $end
$var reg 1 ' coin_5 $end
$var reg 1 ( rst $end
$var reg 2 ) select [1:0] $end
$scope module uut $end
$var wire 1 * cancel $end
$var wire 1 + clk $end
$var wire 1 , coin_10 $end
$var wire 1 - coin_5 $end
$var wire 1 . rst $end
$var wire 2 / select [1:0] $end
$var reg 8 0 balance [7:0] $end
$var reg 1 1 dispense $end
$var reg 2 2 next_state [1:0] $end
$var reg 8 3 price [7:0] $end
$var reg 2 4 product_id [1:0] $end
$var reg 1 5 refund $end
$var reg 2 6 state [1:0] $end
$upscope $end
$upscope $end
$enddefinitions $end
#0
$dumpvars
b0 6
05
b0 4
b1010 3
b0 2
01
b0 0
b0 /
1.
0-
0,
0+
0*
b0 )
1(
0'
0&
0%
0$
0#
b0 "
0!
$end
#5000
1%
1+
#10000
0%
0+
#15000
b1111 3
b1 4
b1 "
b1 6
b1 2
1%
1+
b1 )
b1 /
0(
0.
#20000
0%
0+
#25000
1%
1+
b0 )
b0 /
#30000
0%
0+
#35000
b1010 0
1%
1+
1&
1,
#40000
0%
0+
#45000
1%
1+
0&
0,
#50000
0%
0+
#55000
b10 2
b1111 0
1%
1+
1'
1-
#60000
0%
0+
#65000
b0 2
11
1!
b10 6
1%
1+
0'
0-
#70000
0%
0+
#75000
01
0!
b0 0
b0 6
1%
1+
#80000
0%
0+
#85000
1%
1+
#90000
0%
0+
#95000
b10100 3
b10 4
b10 "
b1 6
b1 2
1%
1+
b10 )
b10 /
#100000
0%
0+
#105000
1%
1+
b0 )
b0 /
#110000
0%
0+
#115000
b1010 0
1%
1+
1&
1,
#120000
0%
0+
#125000
1%
1+
0&
0,
#130000
0%
0+
#135000
15
1#
b11 6
b0 2
1%
1+
1$
1*
#140000
0%
0+
#145000
b0 0
b0 6
05
0#
b0 2
1%
1+
0$
0*
#150000
0%
0+
#155000
1%
1+
#160000
0%
0+
#165000
1%
1+
#170000
0%
0+
#175000
1%
1+
#180000
0%
0+
#185000
b11001 3
b11 4
b11 "
b1 6
b1 2
1%
1+
b11 )
b11 /
#190000
0%
0+
#195000
1%
1+
b0 )
b0 /
#200000
0%
0+
#205000
b1010 0
1%
1+
1&
1,
#210000
0%
0+
#215000
1%
1+
0&
0,
#220000
0%
0+
#225000
b10100 0
1%
1+
1&
1,
#230000
0%
0+
#235000
1%
1+
0&
0,
#240000
0%
0+
#245000
b10 2
b11110 0
1%
1+
1&
1,
#250000
0%
0+
#255000
b0 2
11
1!
b10 6
1%
1+
0&
0,
#260000
0%
0+
#265000
01
0!
b0 0
b0 6
1%
1+
